nerxiv/__init__.py
nerxiv/_version.py
nerxiv/chunker.py
nerxiv/logger.py
nerxiv/cli/__init__.py
nerxiv/cli/cli.py
nerxiv/datamodel/__init__.py
nerxiv/datamodel/analytical_continuation.py
nerxiv/datamodel/base_section.py
nerxiv/datamodel/crystal_structure.py
nerxiv/datamodel/dft.py
nerxiv/datamodel/dmft.py
nerxiv/datamodel/example.json
nerxiv/datamodel/interactions.py
nerxiv/datamodel/projection.py
nerxiv/parsing/__init__.py
nerxiv/prompts/__init__.py
nerxiv/prompts/filters_registry.py
nerxiv/prompts/prompts.py
nerxiv/prompts/prompts_registry.py
nerxiv/rag/__init__.py
nerxiv/rag/agents.py
nerxiv/rag/generator.py
nerxiv/rag/retriever.py
nerxiv/utils/__init__.py
nerxiv/utils/caching.py
nerxiv/utils/utils.py
nerxiv-1.0.1.dist-info/licenses/LICENSE
tests/__init__.py
tests/conftest.py
tests/test_chunker.py
tests/test_logger.py
tests/cli/test_cli.py
tests/data/2502.12144v1.pdf
tests/data/no_pdf_paper.txt
tests/data/sample.pdf
tests/prompts/test_prompts.py
tests/rag/test_agents.py
tests/rag/test_generator.py
tests/rag/test_retriever.py
tests/utils/test_caching.py
tests/utils/test_utils.py
nerxiv-1.0.1.dist-info/METADATA
nerxiv-1.0.1.dist-info/WHEEL
nerxiv-1.0.1.dist-info/entry_points.txt
nerxiv-1.0.1.dist-info/top_level.txt
nerxiv-1.0.1.dist-info/RECORD
