Metadata-Version: 2.4
Name: nerxiv
Version: 1.0.1
Summary: A Python package for extracting structured metadata information from arXiv papers.
Author-email: "Jose M. Pizarro" <jose.pizarro-blanco@bam.de>
Maintainer-email: "Jose M. Pizarro" <jose.pizarro-blanco@bam.de>
License: Copyright (c) 2025 Jose M. Pizarro
Project-URL: Homepage, https://github.com/JosePizarro3/NERxiv
Project-URL: Bug Tracker, https://github.com/JosePizarro3/NERxiv/issues
Classifier: Natural Language :: English
Classifier: Intended Audience :: Science/Research
Classifier: Operating System :: OS Independent
Classifier: Programming Language :: Python
Classifier: Programming Language :: Python :: 3.10
Classifier: Programming Language :: Python :: 3.11
Classifier: Programming Language :: Python :: 3.12
Requires-Python: >=3.10
License-File: LICENSE
Requires-Dist: click>=8.2.1
Requires-Dist: sentence-transformers
Requires-Dist: langchain-core>=0.3.20
Requires-Dist: langchain-ollama
Requires-Dist: langchain-huggingface
Requires-Dist: langchain-text-splitters
Requires-Dist: pyrxiv>=1.0.1
Requires-Dist: pymatgen
Requires-Dist: spacy
Requires-Dist: h5py~=3.12.1
Requires-Dist: structlog~=24.4.0
Provides-Extra: dev
Requires-Dist: mypy>=1.8.0; extra == "dev"
Requires-Dist: ruff; extra == "dev"
Requires-Dist: pytest; extra == "dev"
Requires-Dist: pytest-timeout; extra == "dev"
Requires-Dist: pytest-cov; extra == "dev"
Requires-Dist: python-decouple; extra == "dev"
Provides-Extra: docu
Requires-Dist: marimo[recommended]; extra == "docu"
Requires-Dist: mkdocs-material; extra == "docu"
Requires-Dist: mkdocs-click; extra == "docu"
Requires-Dist: mkdocstrings; extra == "docu"
Requires-Dist: mkdocstrings-python; extra == "docu"
Requires-Dist: mike; extra == "docu"
Dynamic: license-file
